{"videos":[{"y_id":"dHRgGIGrXRE","status":"found","date":"11/03/2016","y_title":"Top 5 NBA Plays: November 3rd","type":"default"},{"status":"found","type":"default","y_title":"Top 10 NBA Plays: November 2nd","date":"11/02/2016","y_id":"Z6p0JUpGt50"},{"status":"found","date":"11/01/2016","y_title":"Top 10 NBA Plays of the Night 11.01.2016","type":"default","y_id":"trn72T7eqSU"},{"type":"default","y_title":"Top 10 NBA State Farm Assists of the Week: 10/25 - 10/29","date":"10/31/2016","status":"found","y_id":"eJ2EEK7VELY"},{"y_id":"iwG1gJSIvds","type":"default","date":"10/30/2016","y_title":"Top 10 NBA Plays: October 30th","status":"found"},{"y_id":"Tqhb3OXpCjM","type":"default","y_title":"Top 10 NBA Plays: October 29th","date":"10/29/2016","status":"found"},{"y_id":"JWy8L0Q0Ik0","status":"found","date":"10/28/2016","y_title":"Top 10 NBA Plays: October 28th","type":"default"},{"y_id":"9KDciqdnrts","status":"found","type":"default","y_title":"Top 5 NBA Plays: October 27th","date":"10/27/2016"},{"y_id":"G9BUuLVvlfc","y_title":"Top 10 NBA Plays: October 26th","date":"10/26/2016","type":"default","status":"found"},{"y_id":"e4qNmYJfGqQ","status":"found","type":"default","date":"10/25/2016","y_title":"Top 10 NBA Plays: October 25th"},{"status":"found","y_title":"Top 10 NBA Plays: April 23rd","date":"04/23/2016","type":"default","y_id":"HNYxHizWeBo"},{"type":"default","y_title":"Top 5 NBA Plays: April 22nd","date":"04/22/2016","status":"found","y_id":"Cdiz_47IoG8"},{"y_id":"s2MV8n0dPrY","y_title":"Top 5 NBA Plays: April 21st","date":"04/21/2016","type":"default","status":"found"},{"status":"found","y_title":"Top 5 NBA Plays: April 20th","date":"04/20/2016","type":"default","y_id":"xuB-en_gUr4"},{"status":"found","type":"default","date":"04/19/2016","y_title":"Top 5 NBA Plays: April 19th","y_id":"FcXL7STc9yw"},{"y_id":"XqV7b8WDTJ8","status":"found","y_title":"Top 5 NBA Plays: April 18th","date":"04/18/2016","type":"default"},{"y_title":"Top 10 NBA Plays: April 17th","date":"04/17/2016","type":"default","status":"found","y_id":"xHbRnZQ_tgc"},{"y_id":"-OOQcrjqYrY","status":"found","date":"04/16/2016","y_title":"Top 5 NBA Plays: April 16, 2016","type":"default"},{"y_id":"","y_title":"","date":"04/15/2016","type":"default","status":"not found"},{"y_id":"JUhTHJ0mwKQ","status":"found","type":"default","y_title":"Top 10 NBA Plays: April 13th","date":"04/14/2016"},{"y_id":"JUhTHJ0mwKQ","status":"found","y_title":"Top 10 NBA Plays: April 13th","date":"04/13/2016","type":"default"},{"y_title":"Top 5 NBA Plays: April 12th","date":"04/12/2016","type":"default","status":"found","y_id":"LfMKn-cVHeY"},{"type":"default","y_title":"Top 10 NBA Plays: April 11th","date":"04/11/2016","status":"found","y_id":"FVTYLQFZNDY"},{"y_id":"WJaVkZD9EKY","y_title":"Top 10 NBA Plays: April 10th","date":"04/10/2016","type":"default","status":"found"},{"y_id":"RkS0tFRS3EQ","status":"found","y_title":"Top 5 NBA Plays: April 9th","date":"04/09/2016","type":"default"},{"date":"04/08/2016","y_title":"Top 10 NBA Plays: April 8th","type":"default","status":"found","y_id":"jt3KFKonV8o"},{"y_id":"eZlVi81Ws78","date":"04/07/2016","y_title":"Top 5 NBA Plays: April 7th","type":"default","status":"found"},{"y_id":"fhizqVw8Nyo","status":"found","y_title":"Top 5 NBA Plays: April 6th","date":"04/06/2016","type":"default"},{"y_id":"jhZPsqCDfiQ","y_title":"Top 10 NBA Plays: April 5th","date":"04/05/2016","type":"default","status":"found"},{"y_id":"oFIfJacwhDw","status":"found","type":"default","y_title":"Top 10 NBA Plays: April 3rd","date":"04/04/2016"},{"status":"found","date":"04/03/2016","y_title":"Top 10 NBA Plays: April 3rd","type":"default","y_id":"oFIfJacwhDw"},{"y_title":"Top 5 NBA Plays: April 2nd","date":"04/02/2016","type":"default","status":"found","y_id":"V4iZFLnOIQw"},{"status":"found","date":"04/01/2016","y_title":"Top 10 NBA Plays: April 1st","type":"default","y_id":"yV4WS_zerfg"},{"y_id":"9mdKBHzTuRA","status":"found","type":"default","y_title":"Top 5 NBA Plays: March 31st","date":"03/31/2016"},{"type":"default","date":"03/30/2016","y_title":"Top 10 NBA Plays: March 30th","status":"found","y_id":"fSWRIqYOXcA"},{"y_id":"NjNE1a4PIug","status":"found","date":"03/29/2016","y_title":"Top 5 NBA Plays: March 29th","type":"default"},{"status":"found","date":"03/28/2016","y_title":"Top 10 NBA Plays: March 28th","type":"default","y_id":"fi9OZUOZlgQ"},{"y_title":"Top 5 NBA Plays: March 27th","date":"03/27/2016","type":"default","status":"found","y_id":"677z1eIkIyM"},{"type":"default","y_title":"Top 10 NBA Plays: March 26th","date":"03/26/2016","status":"found","y_id":"DHLcRLkK6y4"},{"y_id":"EggZBoGREhw","date":"03/25/2016","y_title":"Top 10 NBA Plays: March 25th","type":"default","status":"found"},{"status":"found","date":"03/24/2016","y_title":"Top 5 NBA Plays: March 24th","type":"default","y_id":"ddrCtPlUmm0"},{"status":"found","type":"default","y_title":"Top 10 NBA Plays: March 23rd","date":"03/23/2016","y_id":"_llB8xEN3QA"},{"date":"03/22/2016","y_title":"Top 5 NBA Plays: March 22nd","type":"default","status":"found","y_id":"SVOgqf_D5nU"},{"y_id":"7xjCIiC9kmo","type":"default","date":"03/21/2016","y_title":"Top 10 NBA Plays: March 21st","status":"found"},{"y_id":"Al4COJINt7Y","status":"found","y_title":"Top 10 NBA Plays: March 20th","date":"03/20/2016","type":"default"},{"y_id":"WGwNh4YvHP8","status":"found","date":"03/19/2016","y_title":"Top 10 NBA Plays: March 19th","type":"default"},{"status":"found","type":"default","y_title":"Top 10 NBA Plays: March 18th","date":"03/18/2016","y_id":"V7JCtSJCTcw"},{"date":"03/17/2016","y_title":"Top 10 NBA Plays: March 17th","type":"default","status":"found","y_id":"Ro_U9yO5kVc"},{"y_id":"YiqzDTeR9WI","type":"default","y_title":"Top 10 NBA Plays: March 16","date":"03/16/2016","status":"found"},{"y_id":"_XrwZBtfksk","status":"found","type":"default","y_title":"Top 10 NBA Plays: March 15","date":"03/15/2016"},{"y_id":"YH2gqDeSL9w","date":"03/14/2016","y_title":"Top 10 NBA Plays: March 14th","type":"default","status":"found"},{"type":"default","y_title":"Top 10 NBA Plays: March 13th","date":"03/13/2016","status":"found","y_id":"0GOmNqrbLfM"},{"y_id":"a2gJm9BcHsU","type":"default","y_title":"Top 10 Plays: March 12th","date":"03/12/2016","status":"found"},{"status":"found","type":"default","date":"03/11/2016","y_title":"Top 10 NBA Plays: March 11th","y_id":"prom0AAImmY"},{"y_id":"zxw5MP1p8Dk","date":"03/10/2016","y_title":"Top 5 NBA Plays: March 10th","type":"default","status":"found"},{"y_title":"Top 10 NBA Plays: March 9th","date":"03/09/2016","type":"default","status":"found","y_id":"4U_B1SOdlZw"},{"status":"found","type":"default","date":"03/08/2016","y_title":"Top 10 NBA Plays: March 8th","y_id":"LkkjcdMLW9c"},{"date":"03/07/2016","y_title":"Top 10 NBA Plays: March 7th","type":"default","status":"found","y_id":"D30oZm45N5w"},{"y_id":"8mrY_Nshh4A","status":"found","type":"default","date":"03/06/2016","y_title":"Top 10 NBA Plays: March 6, 2016"},{"y_id":"Rq5Pp_Fc8N4","status":"found","y_title":"Top 10 NBA Plays: March 5th","date":"03/05/2016","type":"default"},{"date":"03/04/2016","y_title":"Top 10 NBA Plays: March 4th","type":"default","status":"found","y_id":"B8NdLMWyQb4"},{"y_id":"f4xhceWx52o","y_title":"Top 10 NBA Plays: March 3rd","date":"03/03/2016","type":"default","status":"found"},{"y_id":"umtVowYKQaI","status":"found","type":"default","date":"03/02/2016","y_title":"Top 10 NBA Plays: March 2nd"},{"y_id":"WGxwRBbu5lI","status":"found","date":"03/01/2016","y_title":"Top 5 NBA Plays: March 1st","type":"default"},{"y_id":"4PoFjye4E1s","status":"found","type":"default","date":"02/29/2016","y_title":"Top 10 NBA Plays: February 29th"},{"type":"default","y_title":"Top 10 NBA Plays: February 28th","date":"02/28/2016","status":"found","y_id":"0KAXB3qlvdk"},{"y_id":"EYGOLV_iz8M","status":"found","type":"default","date":"02/27/2016","y_title":"Top 10 NBA Plays: February 27th"},{"status":"found","y_title":"Top 10 NBA Plays: February 26th","date":"02/26/2016","type":"default","y_id":"i9p2m8kC_4k"},{"y_id":"Y3u5o8Vil34","status":"found","type":"default","date":"02/25/2016","y_title":"Top 10 NBA Plays: February 25th"},{"y_id":"i6CjpRCQvfg","y_title":"Top 10 NBA Plays: February 24th","date":"02/24/2016","type":"default","status":"found"},{"y_id":"Wg2bsV6lCCo","type":"default","date":"02/23/2016","y_title":"Top 10 NBA Plays: February 23rd","status":"found"},{"y_id":"RkfLVW5JZNw","y_title":"Top 10 NBA Plays: February 22nd","date":"02/22/2016","type":"default","status":"found"},{"y_title":"Top 10 NBA Plays: February 21st","date":"02/21/2016","type":"default","status":"found","y_id":"EIBfFG2kFqI"},{"y_id":"JnHsd8P2mEs","type":"default","date":"02/20/2016","y_title":"Top 5 NBA Plays: February 20th","status":"found"},{"status":"found","y_title":"Top 10 NBA Plays: February 19th","date":"02/19/2016","type":"default","y_id":"V9v9Xfu32jY"},{"y_id":"0Mjy8tyiQNs","y_title":"Top 5 NBA Plays: February 18th","date":"02/18/2016","type":"default","status":"found"},{"y_id":"","type":"default","y_title":"","date":"02/17/2016","status":"not found"},{"type":"default","y_title":"","date":"02/16/2016","status":"not found","y_id":""},{"date":"02/15/2016","y_title":"","type":"default","status":"not found","y_id":""},{"y_id":"p-owde8HuDo","type":"default","y_title":"Top 10 NBA Plays: All-Star Sunday","date":"02/14/2016","status":"found"},{"y_id":"X5gaXXOirkY","type":"default","y_title":"Top 10 NBA Plays: All-Star Saturday Night","date":"02/13/2016","status":"found"},{"date":"02/12/2016","y_title":"Top 10 NBA Plays: All-Star Friday Night","type":"default","status":"found","y_id":"PehFOf2cX2U"},{"type":"default","y_title":"Top 5 NBA Plays: February 11th","date":"02/11/2016","status":"found","y_id":"OP3Z_O9ehNM"},{"y_id":"tRbatslZpck","y_title":"Top 10 NBA Plays: February 10th","date":"02/10/2016","type":"default","status":"found"},{"y_id":"W7mPy8otcUk","status":"found","y_title":"Top 10 NBA Plays: February 9th","date":"02/09/2016","type":"default"},{"type":"default","y_title":"Top 10 NBA Plays: February 8th","date":"02/08/2016","status":"found","y_id":"aQLBExupRuw"},{"y_title":"Top 5 NBA Plays: February 7th","date":"02/07/2016","type":"default","status":"found","y_id":"b2Q5O4c0wpk"},{"status":"found","y_title":"Top 10 NBA Plays: February 6th","date":"02/06/2016","type":"default","y_id":"Jir19PVlnL8"},{"y_id":"SzRFLo8YBqI","type":"default","y_title":"Top 10 NBA Plays: February 5th","date":"02/05/2016","status":"found"},{"y_id":"qHcjHLbuWeY","date":"02/04/2016","y_title":"Top 5 NBA Plays: February 4th","type":"default","status":"found"},{"y_id":"tJIQCLsztm0","status":"found","type":"default","date":"02/03/2016","y_title":"Top 10 NBA Plays: February 3rd"},{"status":"found","y_title":"Top 10 NBA Plays: February 2nd","date":"02/02/2016","type":"default","y_id":"HnpkgMFCdMU"},{"status":"found","type":"default","y_title":"Top 10 NBA Plays: February 1st","date":"02/01/2016","y_id":"pMf0eHyfZA4"},{"y_id":"xa60NTndzqY","type":"default","y_title":"Top 10 NBA Plays: January 31st","date":"01/31/2016","status":"found"},{"date":"01/30/2016","y_title":"Top 10 NBA Plays: January 30th","type":"default","status":"found","y_id":"CoGPG4drC4g"},{"status":"found","type":"default","y_title":"Top 10 NBA Plays: January 29","date":"01/29/2016","y_id":"7zYtI-oFv_A"},{"y_id":"Z_PvJJKbiIw","type":"default","date":"01/28/2016","y_title":"Top 10 NBA Plays: January 28th","status":"found"},{"y_title":"Top 10 NBA Plays: January 27th","date":"01/27/2016","type":"default","status":"found","y_id":"Dm-8bjf2wqU"},{"y_id":"g1zxQwGWKeo","status":"found","type":"default","date":"01/26/2016","y_title":"Top 10 NBA Plays: January 26th"},{"status":"found","type":"default","date":"01/25/2016","y_title":"Top 10 NBA Plays: January 25th","y_id":"CVSecC5rVnU"},{"status":"found","type":"default","date":"01/24/2016","y_title":"Top 5 NBA Plays: January 24th","y_id":"Znug4ekJyM0"},{"y_id":"i0fta50o6ik","status":"found","y_title":"Top 10 NBA Plays: January 23rd","date":"01/23/2016","type":"default"},{"y_id":"Zt1xe4v7xlY","y_title":"Top 10 NBA Plays: January 22nd","date":"01/22/2016","type":"default","status":"found"},{"y_id":"ihk08ednrHw","status":"found","date":"01/21/2016","y_title":"Top 10 NBA Plays: January 21st","type":"default"},{"status":"found","date":"01/20/2016","y_title":"Top 10 NBA Plays: January 20th","type":"default","y_id":"qtcN2lr5Ti8"},{"y_id":"I4CJQjyTsys","status":"found","type":"default","y_title":"Top 10 NBA Plays: January 19th","date":"01/19/2016"},{"type":"default","date":"01/18/2016","y_title":"Top 10 NBA Plays: January 18th","status":"found","y_id":"Vuf2oHk6FQU"},{"date":"01/17/2016","y_title":"Top 10 NBA Plays: January 17th","type":"default","status":"found","y_id":"UThdCVqxgYc"},{"y_id":"MZQN160NVHc","status":"found","type":"default","y_title":"Top 10 NBA Plays: January 16th","date":"01/16/2016"},{"y_id":"LHEQvghTBWc","status":"found","date":"01/15/2016","y_title":"Top 10 NBA Plays: January 15th","type":"default"},{"y_id":"GuPfLN9nKD8","status":"found","y_title":"Top 10 NBA Plays: January 14th","date":"01/14/2016","type":"default"},{"y_id":"Bajoh49eSwQ","status":"found","date":"01/13/2016","y_title":"Top 10 NBA Plays: January 13th","type":"default"},{"y_title":"Top 10 NBA Plays: January 12th","date":"01/12/2016","type":"default","status":"found","y_id":"nEiaGpdug0M"},{"y_id":"6pxu7ibwuDY","type":"default","y_title":"Top 5 NBA Plays: January 11th","date":"01/11/2016","status":"found"},{"y_id":"ixRWxTvlr0c","status":"found","type":"default","date":"01/10/2016","y_title":"Top 10 NBA Plays: January 10th"},{"y_id":"xbYlL2ztmEs","y_title":"Top 10 NBA Plays: January 9th","date":"01/09/2016","type":"default","status":"found"},{"status":"found","y_title":"Top 10 NBA Plays: January 8th","date":"01/08/2016","type":"default","y_id":"qajcNTk6dTg"},{"y_id":"-AXESveBybY","status":"found","date":"01/07/2016","y_title":"Top 10 NBA Plays: January 7th","type":"default"},{"y_id":"jPTa78AA3NY","status":"found","type":"default","date":"01/06/2016","y_title":"Top 10 NBA Plays: January 6th"},{"status":"found","y_title":"Top 10 NBA Plays: January 5th","date":"01/05/2016","type":"default","y_id":"VlxaSmjtbuc"},{"y_id":"tPxtDiurh18","date":"01/03/2016","y_title":"Top 10 NBA Plays: January 3rd","type":"default","status":"found"},{"y_id":"vDSt2ZhRyG8","date":"01/02/2016","y_title":"Top 10 NBA Plays: January 2nd","type":"default","status":"found"},{"y_id":"v89ksIGcv_s","status":"found","date":"01/01/2016","y_title":"Top 10 NBA Plays: January 1st","type":"default"},{"y_id":"zigClDn8BRI","status":"found","type":"default","y_title":"Top 10 NBA Plays: December 31st","date":"12/31/2015"},{"y_id":"89_V5CN6gvg","status":"found","type":"default","date":"12/30/2015","y_title":"Top 10 NBA Plays: December 30th"},{"type":"default","y_title":"Top 10 NBA Plays: December 29th","date":"12/29/2015","status":"found","y_id":"yM4bsDkZSVs"},{"y_id":"jsCupE0II1Y","status":"found","date":"12/28/2015","y_title":"Top 10 NBA Plays: December 28th","type":"default"},{"y_id":"HViuyJZ2WHQ","type":"default","date":"12/27/2015","y_title":"Top 10 NBA Plays: December 27th","status":"found"},{"y_id":"zOYJMjjk-X8","status":"found","date":"12/26/2015","y_title":"Top 10 NBA Plays: December 26th","type":"default"},{"y_title":"Top 10 NBA Plays: 2015 Christmas Day","date":"12/25/2015","type":"default","status":"found","y_id":"h7YUPi2rDpw"},{"type":"default","date":"12/23/2015","y_title":"Top 10 NBA Plays: December 23rd","status":"found","y_id":"PmEPoebkMxY"},{"y_id":"agBLbmGqXZQ","status":"found","y_title":"Top 5 NBA Plays: December 22nd","date":"12/22/2015","type":"default"},{"date":"12/21/2015","y_title":"Top 10 NBA Plays: December 21st","type":"default","status":"found","y_id":"9xv0HEhcehg"},{"y_id":"Somy71sJQFM","type":"default","y_title":"Top 5 NBA Plays: December 19th","date":"12/19/2015","status":"found"},{"status":"found","date":"12/18/2015","y_title":"Top 10 NBA Plays: December 18th","type":"default","y_id":"xVZAWt_-KPA"},{"y_id":"vdUbhCyk814","type":"default","y_title":"Top 10 NBA Plays: December 17th","date":"12/17/2015","status":"found"},{"status":"found","type":"default","y_title":"Top 10 NBA Plays: December 16th","date":"12/16/2015","y_id":"EH1Ltc9G_XI"},{"y_id":"w9IeQBv3ADk","date":"12/15/2015","y_title":"Top 5 NBA Plays: December 15th","type":"default","status":"found"},{"y_id":"RDIW5a72w2Y","status":"found","type":"default","y_title":"Top 10 NBA Plays: December 14th","date":"12/14/2015"},{"y_title":"Top 5 NBA Plays: December 13th","date":"12/13/2015","type":"default","status":"found","y_id":"C-gdTrSsGxg"},{"y_id":"5BFeInvc4OY","status":"found","y_title":"Top 10 NBA Plays: December 12th","date":"12/12/2015","type":"default"},{"status":"found","type":"default","y_title":"Top 10 NBA Plays: December 11th","date":"12/11/2015","y_id":"8sGt_La_w8E"},{"y_id":"NNJeTOBmDCI","status":"found","type":"default","date":"12/10/2015","y_title":"Top 10 NBA Plays: December 10th"},{"y_id":"1pzkjsCwK_o","y_title":"Top 10 NBA Plays: December 9th","date":"12/09/2015","type":"default","status":"found"},{"y_id":"yRIhlw5N9rY","status":"found","y_title":"Top 10 NBA Plays: December 8th","date":"12/08/2015","type":"default"},{"y_id":"h_oBhGiSiZ4","type":"default","date":"12/07/2015","y_title":"Top 10 NBA Plays: December 7th","status":"found"},{"status":"found","type":"default","y_title":"Top 10 NBA Plays: December 6th","date":"12/06/2015","y_id":"rWaa2NggnM8"},{"type":"default","y_title":"Top 10 NBA Plays: December 5th","date":"12/05/2015","status":"found","y_id":"MsprTMqtJEc"},{"y_id":"BMAhiTVxxq0","type":"default","y_title":"Top 10 NBA Plays: December 4th","date":"12/04/2015","status":"found"},{"y_title":"Top 10 NBA Plays: December 3rd","date":"12/03/2015","type":"default","status":"found","y_id":"uOcWeKZVYGI"},{"y_title":"Top 10 NBA Plays: December 2nd","date":"12/02/2015","type":"default","status":"found","y_id":"c8bheDqGIt4"},{"y_id":"Y4eudqJoi0k","status":"found","y_title":"Top 10 NBA Plays: December 1st","date":"12/01/2015","type":"default"},{"y_title":"Top 10 NBA Plays: November 30th","date":"11/30/2015","type":"default","status":"found","y_id":"Xm57Rp4KwnY"},{"y_id":"DVadnWUBzvA","status":"found","type":"default","date":"11/29/2015","y_title":"Top 10 NBA Plays: November 29th"},{"type":"default","date":"11/28/2015","y_title":"Top 10 NBA Plays: November 28th","status":"found","y_id":"LRq6WY0-pxw"},{"y_title":"Top 10 NBA Plays: November 27th","date":"11/27/2015","type":"default","status":"found","y_id":"na4sTmg_4I4"},{"status":"found","type":"default","y_title":"Top 10 NBA Plays: November 25th","date":"11/25/2015","y_id":"bcpKQywHhIM"},{"status":"found","type":"default","y_title":"Top 10 NBA Plays: November 24th","date":"11/24/2015","y_id":"LczTXpz-4T0"},{"date":"11/23/2015","y_title":"Top 10 NBA Plays: November 23rd","type":"default","status":"found","y_id":"AW1sKgAaXNk"},{"y_title":"Top 10 NBA Plays: November 22nd","date":"11/22/2015","type":"default","status":"found","y_id":"-MCe4ZfLxuM"},{"y_id":"b0W4dkTs9Tg","status":"found","type":"default","date":"11/21/2015","y_title":"Top 10 NBA Plays: November 21st"},{"status":"found","type":"default","y_title":"Top 10 NBA Plays: November 20th","date":"11/20/2015","y_id":"FBxH7hK-RQs"},{"type":"default","date":"11/19/2015","y_title":"Top 5 NBA Plays: November 19th","status":"found","y_id":"Ip-oLkQQKA8"},{"y_id":"aUjxxuh4WYQ","type":"default","date":"11/18/2015","y_title":"Top 10 NBA Plays: November 18th","status":"found"},{"y_id":"xy3g3U6nslw","status":"found","date":"11/17/2015","y_title":"Top 10 NBA Plays: November 17th","type":"default"},{"y_title":"Top 10 NBA Plays: November 16th","date":"11/16/2015","type":"default","status":"found","y_id":"Ii_8F1ahqqY"},{"y_id":"KvSS44PLpZc","y_title":"Top 10 NBA Plays: November 15th","date":"11/15/2015","type":"default","status":"found"},{"status":"found","type":"default","date":"11/14/2015","y_title":"Top 10 NBA Plays: November 14th","y_id":"2ImCckT3ums"},{"y_id":"ttbP0BUcBEU","date":"11/13/2015","y_title":"Top 10 NBA Plays: November 13th","type":"default","status":"found"},{"y_title":"Top 10 NBA Plays: November 12th","date":"11/12/2015","type":"default","status":"found","y_id":"U2JTHxH0Dc0"},{"y_id":"UHdHJE3PSws","status":"found","type":"default","date":"11/11/2015","y_title":"Top 10 NBA Plays: November 11th"},{"y_id":"Irm8x-louTM","status":"found","type":"default","date":"11/10/2015","y_title":"Top 10 NBA Plays: November 10th"},{"y_id":"V9WKASxj4iQ","status":"found","type":"default","y_title":"Top 10 NBA Plays: November 9th","date":"11/09/2015"},{"y_id":"63A2SJCfKGc","date":"11/08/2015","y_title":"Top 5 NBA Plays: November 8th","type":"default","status":"found"},{"status":"found","y_title":"Top 10 NBA Plays: November 7th","date":"11/07/2015","type":"default","y_id":"TZRlH6xJ1Mg"},{"date":"11/06/2015","y_title":"Top 10 NBA Plays: November 6th","type":"default","status":"found","y_id":"SsJQKOJSWfU"},{"y_id":"PCCUr73QsM4","status":"found","type":"default","y_title":"Top 10 NBA Plays: November 5th","date":"11/05/2015"},{"y_id":"NalHgDW3kxw","type":"default","y_title":"Top 10 NBA Plays: November 4th","date":"11/04/2015","status":"found"},{"date":"11/03/2015","y_title":"Top 10 NBA Plays: November 3rd","type":"default","status":"found","y_id":"OlHnD02GmDE"},{"y_id":"pLC9rgVOImc","y_title":"Top 10 NBA Plays: November 2nd","date":"11/02/2015","type":"default","status":"found"},{"y_id":"FHh9Jw9OG6s","status":"found","type":"default","y_title":"Top 10 NBA Plays: November 1st","date":"11/01/2015"},{"y_id":"2_AOMSi1vuA","status":"found","type":"default","date":"10/31/2015","y_title":"Top 10 NBA Plays: October 31st"},{"status":"found","type":"default","date":"10/30/2015","y_title":"Top 10 NBA Plays: October 30th","y_id":"1ZHQ7SrHHTk"},{"type":"default","y_title":"Top 5 NBA Plays: October 29th","date":"10/29/2015","status":"found","y_id":"YYAw5CRLu1w"},{"y_id":"60MOVKYR0_E","date":"10/28/2015","y_title":"Top 10 NBA Plays: October 28th","type":"default","status":"found"},{"y_id":"uE1Nyprv1vI","status":"found","type":"default","date":"10/27/2015","y_title":"Top 10 NBA Plays: October 27"}]}